ChunkyPipes-0.2.2.dist-info/DESCRIPTION.rst
ChunkyPipes-0.2.2.dist-info/METADATA
ChunkyPipes-0.2.2.dist-info/RECORD
ChunkyPipes-0.2.2.dist-info/WHEEL
ChunkyPipes-0.2.2.dist-info/entry_points.txt
ChunkyPipes-0.2.2.dist-info/metadata.json
ChunkyPipes-0.2.2.dist-info/top_level.txt
chunkypipes/__init__.py
chunkypipes/components/__init__.py
chunkypipes/util/__init__.py
chunkypipes/util/base.py
chunkypipes/util/commands/__init__.py
chunkypipes/util/commands/configure.py
chunkypipes/util/commands/help.py
chunkypipes/util/commands/init.py
chunkypipes/util/commands/install.py
chunkypipes/util/commands/list.py
chunkypipes/util/commands/run.py
