Metadata-Version: 2.0
Name: ChunkyPipes
Version: 0.2.2
Summary: Pipeline design and distribution framework
Home-page: https://github.com/djf604/chunky-pipes
Author: Dominic Fitzgerald
Author-email: dominicfitzgerald11@gmail.com
License: MIT
Download-URL: https://github.com/djf604/chunky-pipes/tarball/0.2.2
Platform: UNKNOWN
Classifier: Development Status :: 3 - Alpha
Classifier: Environment :: Console
Classifier: Intended Audience :: Developers
Classifier: Intended Audience :: Science/Research
Classifier: Programming Language :: Python
Classifier: Programming Language :: Python :: 2.7
Classifier: Topic :: Scientific/Engineering
Classifier: Topic :: Scientific/Engineering :: Bio-Informatics
Classifier: Topic :: Software Development :: Libraries
Classifier: License :: OSI Approved :: MIT License
